config/__init__.py
config/config.yaml
config/load_config.py
document_processing/__init__.py
document_processing/chunking.py
document_processing/parser.py
embeddings/__init__.py
embeddings/embedding.py
llm/__init__.py
llm/claude.py
llm/gpt.py
llm/opensource.py
vectorstore/__init__.py
vectorstore/deeplake_db.py
vectorstore/weaviate_db.py
armenian_rag-0.5.0.dist-info/METADATA
armenian_rag-0.5.0.dist-info/WHEEL
armenian_rag-0.5.0.dist-info/top_level.txt
armenian_rag-0.5.0.dist-info/RECORD
