Metadata-Version: 2.1
Name: armenian-rag
Version: 0.5.0
Classifier: Programming Language :: Python :: 3
Classifier: License :: OSI Approved :: MIT License
Classifier: Operating System :: OS Independent
Requires-Python: >=3.6
Requires-Dist: aiofiles ==23.2.1
Requires-Dist: annotated-types ==0.7.0
Requires-Dist: anthropic ==0.37.1
Requires-Dist: anyio ==4.6.2.post1
Requires-Dist: asyncer ==0.0.7
Requires-Dist: Authlib ==1.3.1
Requires-Dist: bidict ==0.23.1
Requires-Dist: boto3 ==1.35.52
Requires-Dist: botocore ==1.35.52
Requires-Dist: certifi ==2024.8.30
Requires-Dist: cffi ==1.17.1
Requires-Dist: chainlit ==1.3.1
Requires-Dist: charset-normalizer ==3.4.0
Requires-Dist: chevron ==0.14.0
Requires-Dist: click ==8.1.7
Requires-Dist: colorama ==0.4.6
Requires-Dist: cryptography ==43.0.3
Requires-Dist: dataclasses-json ==0.6.7
Requires-Dist: deeplake ==3.9.27
Requires-Dist: Deprecated ==1.2.14
Requires-Dist: dill ==0.3.9
Requires-Dist: distro ==1.9.0
Requires-Dist: fastapi ==0.112.4
Requires-Dist: filelock ==3.16.1
Requires-Dist: filetype ==1.2.0
Requires-Dist: fsspec ==2024.10.0
Requires-Dist: googleapis-common-protos ==1.65.0
Requires-Dist: grpcio ==1.67.1
Requires-Dist: grpcio-health-checking ==1.67.1
Requires-Dist: grpcio-tools ==1.67.1
Requires-Dist: h11 ==0.14.0
Requires-Dist: httpcore ==1.0.6
Requires-Dist: httpx ==0.27.0
Requires-Dist: huggingface-hub ==0.26.2
Requires-Dist: humbug ==0.3.2
Requires-Dist: idna ==3.10
Requires-Dist: importlib-metadata ==8.4.0
Requires-Dist: Jinja2 ==3.1.4
Requires-Dist: jiter ==0.6.1
Requires-Dist: jmespath ==1.0.1
Requires-Dist: joblib ==1.4.2
Requires-Dist: jsonpatch ==1.33
Requires-Dist: jsonpointer ==3.0.0
Requires-Dist: langchain-core ==0.3.13
Requires-Dist: langchain-text-splitters ==0.3.0
Requires-Dist: langsmith ==0.1.137
Requires-Dist: Lazify ==0.4.0
Requires-Dist: literalai ==0.0.623
Requires-Dist: lxml ==5.3.0
Requires-Dist: lz4 ==4.3.3
Requires-Dist: MarkupSafe ==3.0.2
Requires-Dist: marshmallow ==3.23.0
Requires-Dist: mpmath ==1.3.0
Requires-Dist: multiprocess ==0.70.17
Requires-Dist: mypy-extensions ==1.0.0
Requires-Dist: nest-asyncio ==1.6.0
Requires-Dist: networkx ==3.4.2
Requires-Dist: nltk ==3.9.1
Requires-Dist: numpy ==1.26.4
Requires-Dist: openai ==1.52.2
Requires-Dist: opentelemetry-api ==1.27.0
Requires-Dist: opentelemetry-exporter-otlp ==1.27.0
Requires-Dist: opentelemetry-exporter-otlp-proto-common ==1.27.0
Requires-Dist: opentelemetry-exporter-otlp-proto-grpc ==1.27.0
Requires-Dist: opentelemetry-exporter-otlp-proto-http ==1.27.0
Requires-Dist: opentelemetry-instrumentation ==0.48b0
Requires-Dist: opentelemetry-proto ==1.27.0
Requires-Dist: opentelemetry-sdk ==1.27.0
Requires-Dist: opentelemetry-semantic-conventions ==0.48b0
Requires-Dist: orjson ==3.10.10
Requires-Dist: packaging ==23.2
Requires-Dist: pathos ==0.3.3
Requires-Dist: pillow ==10.4.0
Requires-Dist: plum-dispatch ==1.7.4
Requires-Dist: pox ==0.3.5
Requires-Dist: ppft ==1.7.6.9
Requires-Dist: protobuf <6.0.0.dev0,>=3.20.2
Requires-Dist: pycparser ==2.22
Requires-Dist: pydantic ==2.9.2
Requires-Dist: pydantic-core ==2.23.4
Requires-Dist: PyJWT ==2.9.0
Requires-Dist: PyPDF2 ==3.0.1
Requires-Dist: python-dateutil ==2.9.0.post0
Requires-Dist: python-docx ==1.1.2
Requires-Dist: python-dotenv ==1.0.1
Requires-Dist: python-engineio ==4.10.1
Requires-Dist: python-multipart ==0.0.9
Requires-Dist: python-socketio ==5.11.4
Requires-Dist: PyYAML ==6.0.2
Requires-Dist: regex ==2024.9.11
Requires-Dist: requests ==2.32.3
Requires-Dist: requests-toolbelt ==1.0.0
Requires-Dist: s3transfer ==0.10.3
Requires-Dist: safetensors ==0.4.5
Requires-Dist: scikit-learn ==1.5.2
Requires-Dist: scipy ==1.14.1
Requires-Dist: sentence-transformers ==3.2.1
Requires-Dist: setuptools ==75.3.0
Requires-Dist: simple-websocket ==1.1.0
Requires-Dist: six ==1.16.0
Requires-Dist: sniffio ==1.3.1
Requires-Dist: Spire.Doc ==12.7.1
Requires-Dist: starlette ==0.37.2
Requires-Dist: sympy ==1.13.1
Requires-Dist: syncer ==2.0.3
Requires-Dist: tabulate ==0.9.0
Requires-Dist: tenacity ==9.0.0
Requires-Dist: threadpoolctl ==3.5.0
Requires-Dist: tokenizers ==0.20.1
Requires-Dist: tomli ==2.0.2
Requires-Dist: torch ==2.5.1
Requires-Dist: tqdm ==4.66.6
Requires-Dist: transformers ==4.46.1
Requires-Dist: typing-inspect ==0.9.0
Requires-Dist: typing-extensions ==4.12.2
Requires-Dist: uptrace ==1.27.0
Requires-Dist: urllib3 ==2.2.3
Requires-Dist: uvicorn ==0.25.0
Requires-Dist: validators ==0.34.0
Requires-Dist: watchfiles ==0.20.0
Requires-Dist: weaviate-client ==4.9.0
Requires-Dist: wrapt ==1.16.0
Requires-Dist: wsproto ==1.2.0
Requires-Dist: zipp ==3.20.2
Requires-Dist: pypdf ==5.1.0
